mpishell/__init__.py
mpishell/wrapped_process.py
mpishell-0.2.0.data/scripts/mpishell
mpishell-0.2.0.dist-info/LICENSE
mpishell-0.2.0.dist-info/METADATA
mpishell-0.2.0.dist-info/WHEEL
mpishell-0.2.0.dist-info/top_level.txt
mpishell-0.2.0.dist-info/RECORD
