Metadata-Version: 2.1
Name: mpishell
Version: 0.2.0
Summary: A small program for interactive sessions with MPI applications.
Home-page: https://github.com/loic-ehrhardt/mpishell
Author: Loïc Ehrhardt
License: UNKNOWN
Project-URL: Bug Tracker, https://github.com/loic-ehrhardt/mpishell/issues
Platform: UNKNOWN
Classifier: Programming Language :: Python :: 3
Classifier: License :: OSI Approved :: GNU General Public License v3 (GPLv3)
Classifier: Operating System :: OS Independent
Requires-Python: >=3.6
License-File: LICENSE
Requires-Dist: mpi4py
